calculator_bundle/adder/__init__.py
calculator_bundle.adder-0.1.0.dist-info/METADATA
calculator_bundle.adder-0.1.0.dist-info/WHEEL
calculator_bundle.adder-0.1.0.dist-info/entry_points.txt
calculator_bundle.adder-0.1.0.dist-info/top_level.txt
calculator_bundle.adder-0.1.0.dist-info/RECORD
