Metadata-Version: 2.1
Name: calculator_bundle.adder
Version: 0.1.0
Summary: A simple package to add two numbers.
Author-email: Miguel Jimenez-Urias <mjimenez@opendap.org>
License: MIT
Project-URL: Homepage, https://github.com/Mikejmnez/calculator_bundle.adder
Requires-Python: >=3.10
Provides-Extra: test
Requires-Dist: pytest; extra == "test"
